instr_set.v
`define NOT 5'b00000
`define XOR 5'b00001
`define OR  5'b00010
`define AND 5'b00011
`define SUB 5'b00100
`define ADD 5'b00101 //DATA_MEM
`define RR  5'b00110
`define RL  5'b00111
`define DEC 5'b01000
`define INC 5'b01001
`define LD  5'b01010
`define ST  5'b01011
`define LDR 5'b01100
`define STR 5'b01101

`define BAR 5'b01110 //Base address register - provide base address
`define JMP 5'b01111 //JMP to address
`define JMPO 5'b10000 //JMP for specified offset

`define XORR 5'b10001 //R0-R7
`define ORR  5'b10010
`define ANDR 5'b10011
`define SUBR 5'b10100
`define ADDR 5'b10101 

`define LDI 5'b11010 //Load immediate, differentiates from LD only in fifth bit
`define LDAR 5'b11101 //DATA_MEM address read from R0-R7
`define NOP 5'b11110
`define RST 5'b11111

cpu_id.v
`timescale 1ns/100ps
`include "instr_set.v"

module cpu_id #(
    parameter WIDTH = 13,
    parameter IWIDTH = 5, //Instruction width. Widht of data part -> WIDTH-IWIDTH i.e 13 - 5 = 8 bit Data width
    parameter REG_F_SEL_SIZE = 4, //8 reg + PORT = 9 -> 4 bit
    parameter IN_B_SEL_SIZE = 2 // 00 - IMM, 01 - REG_F, 10 - DATA_MEM
)(
    IN,
    RST,
    PC_LD,
    ALU_OUT,
    IMM,
    IN_B_SEL,
    REG_F_SEL,
    EN_REG_F,
    D_MEM_ADDR,
    D_MEM_ADDR_MODE,  
    EN_D_MEM,
    EN_ACC,
    JMP_MODE,   
    BASE_REG_OFFSET,
    BASE_REG_LD,
    BASE_REG_DATA
);

input [WIDTH-1:0] IN;

output reg RST;
output reg PC_LD;
output reg [IWIDTH-2:0] ALU_OUT; //4 bit
output reg [(WIDTH-IWIDTH)-1:0] IMM;
output reg [IN_B_SEL_SIZE-1:0] IN_B_SEL;

//REG_F
output reg [REG_F_SEL_SIZE-1:0] REG_F_SEL;
output reg EN_REG_F;

//DATA_MEM
output reg [(WIDTH-IWIDTH)-1:0] D_MEM_ADDR;
output reg D_MEM_ADDR_MODE; //0 - ADDR from operand, 1 - ADDR form R0-R7
output reg EN_D_MEM;

output reg EN_ACC;
output reg JMP_MODE; // 0 - absolute, 1 - relative to base address register

//BASE ADDRESS REGISTER
output reg [(WIDTH-IWIDTH)-1:0] BASE_REG_OFFSET;
output reg BASE_REG_LD;
output reg [(WIDTH-IWIDTH)-1:0] BASE_REG_DATA;

//TO DO: STACK, MAIN REGISTER

always @(*) begin
    ALU_OUT = IN[WIDTH-2:(WIDTH-IWIDTH)];
    
    RST = 1'b0;
    PC_LD = 1'b0;
    EN_ACC = 1'b0;
    JMP_MODE = 1'b0;
    
    IN_B_SEL = 2'b10; //DATA_MEM
    IMM = {(WIDTH-IWIDTH){1'b0}};

    REG_F_SEL = {REG_F_SEL_SIZE{1'b0}}; // R0
    EN_REG_F = 1'b0;

    D_MEM_ADDR = {(WIDTH-IWIDTH){1'b0}};
    D_MEM_ADDR_MODE = 1'b0;
    EN_D_MEM = 1'b0;

    BASE_REG_OFFSET = {(WIDTH-IWIDTH){1'b0}};
    BASE_REG_LD = 1'b0;
    BASE_REG_DATA = {(WIDTH-IWIDTH){1'b0}};

    if(IN[WIDTH-1:(WIDTH-IWIDTH)] == `RST) begin
        RST = 1'b1;
    end
    else if(IN[WIDTH-1:(WIDTH-IWIDTH)] == `LD) begin
        D_MEM_ADDR = IN[(WIDTH-IWIDTH)-1:0];
        IN_B_SEL = 2'b10; 
        EN_ACC = 1'b1;
    end
    else if(IN[WIDTH-1:(WIDTH-IWIDTH)] == `ST) begin
        D_MEM_ADDR = IN[(WIDTH-IWIDTH)-1:0];
        EN_D_MEM = 1'b1;
    end
    else if(IN[WIDTH-1:(WIDTH-IWIDTH)] == `LDR) begin
        REG_F_SEL = IN[REG_F_SEL_SIZE-1:0]; //LAST 4 bits of IN
        IN_B_SEL = 2'b01;
        EN_ACC = 1'b1;
    end
    else if(IN[WIDTH-1:(WIDTH-IWIDTH)] == `STR) begin
        REG_F_SEL = IN[REG_F_SEL_SIZE-1:0];
        EN_REG_F = 1'b1;
    end
    else if(IN[WIDTH-1:(WIDTH-IWIDTH)] == `BAR) begin
        BASE_REG_DATA = IN[(WIDTH-IWIDTH)-1:0];
        BASE_REG_LD = 1'b1;
    end
    else if(IN[WIDTH-1:(WIDTH-IWIDTH)] == `JMP) begin
        BASE_REG_OFFSET = IN[(WIDTH-IWIDTH)-1:0];
        JMP_MODE = 1'b0;
        PC_LD = 1'b1;
    end
    else if(IN[WIDTH-1:(WIDTH-IWIDTH)] == `JMPO) begin
        BASE_REG_OFFSET = IN[(WIDTH-IWIDTH)-1:0];
        JMP_MODE = 1'b1;
        PC_LD = 1'b1;
    end
    else if((IN[WIDTH-1:(WIDTH-IWIDTH)] == `XORR) ||
            (IN[WIDTH-1:(WIDTH-IWIDTH)] == `ORR)  ||
            (IN[WIDTH-1:(WIDTH-IWIDTH)] == `ANDR) ||
            (IN[WIDTH-1:(WIDTH-IWIDTH)] == `ADDR) ||
            (IN[WIDTH-1:(WIDTH-IWIDTH)] == `SUBR)
    ) begin
        REG_F_SEL = IN[REG_F_SEL_SIZE-1:0]; 
        IN_B_SEL = 2'b01;
    end
    else if(IN[WIDTH-1:(WIDTH-IWIDTH)] == `LDI) begin
        IMM = IN[(WIDTH-IWIDTH)-1:0];
        IN_B_SEL = 2'b00; 
        EN_ACC = 1'b1;
    end
    else if(IN[WIDTH-1:(WIDTH-IWIDTH)] == `LDAR) begin
        REG_F_SEL = IN[REG_F_SEL_SIZE-1:0];
        D_MEM_ADDR_MODE = 1'b1;
        IN_B_SEL = 2'b10; 
        EN_ACC = 1'b1;
    end
end

endmodule

rom.v
`timescale 1ns/100ps
`include "instr_set.v"

module ROM # (
    parameter AWIDTH = 8,
    parameter DWIDTH = 13
)(
    ADDR,
    DATA
);
input [AWIDTH-1:0] ADDR;
output reg [DWIDTH-1:0] DATA;

always @(*) begin
    case(ADDR) 
        8'h00: DATA = {`LD,8'hAE};
        8'h01: DATA = {`RL,8'h00};
        8'h02: DATA = {`ST,8'hAE};
        8'h03: DATA = {`LDR,8'h04};
        8'h04: DATA = {`INC,8'h00};
        8'h05: DATA = {`STR,8'h02};
        8'h06: DATA = {`LDI,8'h11};
        8'h07: DATA = {`ADDR,8'h01};
        8'h08: DATA = {`STR,8'h01};
        8'h09: DATA = {`BAR,8'h09};
        8'h0A: DATA = {`JMP, 8'h03};
        8'h0B: DATA = `RST;
        8'h0C: DATA = {`JMP,8'h0E};
        8'h0D: DATA = `RST;
        8'h0E: DATA = `NOP;
        8'h0F: DATA = `NOP;
        default: DATA = `RST;
    endcase
end

endmodule

Modules/cpu_pc.v
`timescale 1ns/100ps

module cpu_pc 
#( parameter WIDTH = 8)
(   CLK,
    RST,
    LD,
    ADDR,
    PC_OUT
);

input CLK, RST, LD;
input [WIDTH-1:0] ADDR;
output reg [WIDTH-1:0] PC_OUT;

initial begin
    PC_OUT <= {WIDTH{1'b0}};
end


always @(posedge CLK) begin
    if(RST) begin
        PC_OUT <= {WIDTH{1'b0}};
    end
    else if(LD) begin
        PC_OUT <= ADDR;
    end
    else begin
        PC_OUT <= PC_OUT + 1'b1;
    end

end
    
endmodule

cpu_main.v
`timescale 1ns/100ps

module cpu_main #(
    parameter WIDTH = 13,
    parameter IWIDTH = 5,
    parameter REG_F_SEL_SIZE = 4,
    parameter IN_B_SEL_SIZE = 2
)
(
    CLK
);

input CLK;
wire RST, PC_LD; 
wire [(WIDTH-IWIDTH)-1:0] PC_OUT;
wire [WIDTH-1:0] DATA_TO_ID;
wire [IWIDTH-2:0] ALU_OUT;
wire [(WIDTH-IWIDTH)-1:0] IMM;
wire [IN_B_SEL_SIZE-1:0] IN_B_SEL;
wire [REG_F_SEL_SIZE-1:0] REG_F_SEL;
wire EN_REG_F;
wire [(WIDTH-IWIDTH)-1:0] D_MEM_ADDR;
wire D_MEM_ADDR_MODE;
wire EN_D_MEM;
wire EN_ACC;    
wire JMP_MODE;   
wire [(WIDTH-IWIDTH)-1:0] BASE_REG_OFFSET;
wire BASE_REG_LD;
wire [(WIDTH-IWIDTH)-1:0] BASE_REG_DATA;

cpu_pc #(.WIDTH((WIDTH-IWIDTH))) 
PC (
    .CLK(CLK),
    .RST(RST),
    .LD(PC_LD),
    .ADDR(BASE_REG_OFFSET),
    .PC_OUT(PC_OUT)
);

ROM #(.AWIDTH(WIDTH-IWIDTH),.DWIDTH(WIDTH))
rom (
    .ADDR(PC_OUT),
    .DATA(DATA_TO_ID)
);

cpu_id #(.WIDTH(WIDTH),.IWIDTH(IWIDTH),.REG_F_SEL_SIZE(REG_F_SEL_SIZE), .IN_B_SEL_SIZE(IN_B_SEL_SIZE))
id (
    .IN(DATA_TO_ID),
    .RST(RST),
    .PC_LD(PC_LD),
    .ALU_OUT(ALU_OUT),
    .IMM(IMM),
    .IN_B_SEL(IN_B_SEL),
    .REG_F_SEL(REG_F_SEL),
    .EN_REG_F(EN_REG_F),
    .D_MEM_ADDR(D_MEM_ADDR),
    .D_MEM_ADDR_MODE(D_MEM_ADDR_MODE),
    .EN_D_MEM(EN_D_MEM),
    .EN_ACC(EN_ACC),
    .JMP_MODE(JMP_MODE),   
    .BASE_REG_OFFSET(BASE_REG_OFFSET),
    .BASE_REG_LD(BASE_REG_LD),
    .BASE_REG_DATA(BASE_REG_DATA)  
);


endmodule

cpu_main_tb.v
`timescale 1ns/100ps

module cpu_main_tb;
reg CLK;

cpu_main UUT (
    .CLK(CLK)
);

initial begin
    $display("Simulation of %m started.");
    WAIT(100);
    $finish;
end

// Clock generator
initial begin
	CLK = 1'b0;
	forever #5 CLK = ~CLK;
end

// Writing VCD waveform
initial begin
	$dumpfile("cpu_sim.vcd");
	$dumpvars(0, UUT);
	$dumpon;
end


task WAIT;
input [31:0] DY;
begin
	repeat(DY) @(posedge CLK);
end
endtask

endmodule

cpu_sim.vcd
$date
	Mon Nov  6 15:11:03 2023
$end
$version
	Icarus Verilog
$end
$timescale
	100ps
$end
$scope module cpu_main_tb $end
$scope module UUT $end
$var wire 1 ! CLK $end
$var wire 1 " RST $end
$var wire 4 # REG_F_SEL [3:0] $end
$var wire 8 $ PC_OUT [7:0] $end
$var wire 1 % PC_LD $end
$var wire 1 & JMP_MODE $end
$var wire 2 ' IN_B_SEL [1:0] $end
$var wire 8 ( IMM [7:0] $end
$var wire 1 ) EN_REG_F $end
$var wire 1 * EN_D_MEM $end
$var wire 1 + EN_ACC $end
$var wire 1 , D_MEM_ADDR_MODE $end
$var wire 8 - D_MEM_ADDR [7:0] $end
$var wire 13 . DATA_TO_ID [12:0] $end
$var wire 8 / BASE_REG_OFFSET [7:0] $end
$var wire 1 0 BASE_REG_LD $end
$var wire 8 1 BASE_REG_DATA [7:0] $end
$var wire 4 2 ALU_OUT [3:0] $end
$scope module PC $end
$var wire 1 ! CLK $end
$var wire 1 " RST $end
$var wire 1 % LD $end
$var wire 8 3 ADDR [7:0] $end
$var reg 8 4 PC_OUT [7:0] $end
$upscope $end
$scope module id $end
$var wire 13 5 IN [12:0] $end
$var reg 4 6 ALU_OUT [3:0] $end
$var reg 8 7 BASE_REG_DATA [7:0] $end
$var reg 1 0 BASE_REG_LD $end
$var reg 8 8 BASE_REG_OFFSET [7:0] $end
$var reg 8 9 D_MEM_ADDR [7:0] $end
$var reg 1 , D_MEM_ADDR_MODE $end
$var reg 1 + EN_ACC $end
$var reg 1 * EN_D_MEM $end
$var reg 1 ) EN_REG_F $end
$var reg 8 : IMM [7:0] $end
$var reg 2 ; IN_B_SEL [1:0] $end
$var reg 1 & JMP_MODE $end
$var reg 1 % PC_LD $end
$var reg 4 < REG_F_SEL [3:0] $end
$var reg 1 " RST $end
$upscope $end
$scope module rom $end
$var wire 8 = ADDR [7:0] $end
$var reg 13 > DATA [12:0] $end
$upscope $end
$upscope $end
$upscope $end
$enddefinitions $end
#0
$dumpvars
b101010101110 >
b0 =
b0 <
b10 ;
b0 :
b10101110 9
b0 8
b0 7
b1010 6
b101010101110 5
b0 4
b0 3
b1010 2
b0 1
00
b0 /
b101010101110 .
b10101110 -
0,
1+
0*
0)
b0 (
b10 '
0&
0%
b0 $
b0 #
0"
0!
$end
#50
b0 -
b0 9
0+
b111 2
b111 6
b11100000000 .
b11100000000 5
b11100000000 >
b1 $
b1 4
b1 =
1!
#100
0!
#150
1*
b10101110 -
b10101110 9
b1011 2
b1011 6
b101110101110 .
b101110101110 5
b101110101110 >
b10 $
b10 4
b10 =
1!
#200
0!
#250
1+
b1 '
b1 ;
b100 #
b100 <
0*
b0 -
b0 9
b1100 2
b1100 6
b110000000100 .
b110000000100 5
b110000000100 >
b11 $
b11 4
b11 =
1!
#300
0!
#350
b0 #
b0 <
b10 '
b10 ;
0+
b1001 2
b1001 6
b100100000000 .
b100100000000 5
b100100000000 >
b100 $
b100 4
b100 =
1!
#400
0!
#450
1)
b10 #
b10 <
b1101 2
b1101 6
b110100000010 .
b110100000010 5
b110100000010 >
b101 $
b101 4
b101 =
1!
#500
0!
#550
1+
b0 '
b0 ;
b10001 (
b10001 :
0)
b0 #
b0 <
b1010 2
b1010 6
b1101000010001 .
b1101000010001 5
b1101000010001 >
b110 $
b110 4
b110 =
1!
#600
0!
#650
b1 #
b1 <
b0 (
b0 :
b1 '
b1 ;
0+
b101 2
b101 6
b1010100000001 .
b1010100000001 5
b1010100000001 >
b111 $
b111 4
b111 =
1!
#700
0!
#750
1)
b1 #
b1 <
b10 '
b10 ;
b1101 2
b1101 6
b110100000001 .
b110100000001 5
b110100000001 >
b1000 $
b1000 4
b1000 =
1!
#800
0!
#850
10
b1001 1
b1001 7
0)
b0 #
b0 <
b1110 2
b1110 6
b111000001001 .
b111000001001 5
b111000001001 >
b1001 $
b1001 4
b1001 =
1!
#900
0!
#950
1%
b11 /
b11 3
b11 8
b0 1
b0 7
00
b1111 2
b1111 6
b111100000011 .
b111100000011 5
b111100000011 >
b1010 $
b1010 4
b1010 =
1!
#1000
0!
#1050
1+
b1 '
b1 ;
b100 #
b100 <
b0 /
b0 3
b0 8
0%
b1100 2
b1100 6
b110000000100 .
b110000000100 5
b110000000100 >
b11 $
b11 4
b11 =
1!
#1100
0!
#1150
b0 #
b0 <
b10 '
b10 ;
0+
b1001 2
b1001 6
b100100000000 .
b100100000000 5
b100100000000 >
b100 $
b100 4
b100 =
1!
#1200
0!
#1250
1)
b10 #
b10 <
b1101 2
b1101 6
b110100000010 .
b110100000010 5
b110100000010 >
b101 $
b101 4
b101 =
1!
#1300
0!
#1350
1+
b0 '
b0 ;
b10001 (
b10001 :
0)
b0 #
b0 <
b1010 2
b1010 6
b1101000010001 .
b1101000010001 5
b1101000010001 >
b110 $
b110 4
b110 =
1!
#1400
0!
#1450
b1 #
b1 <
b0 (
b0 :
b1 '
b1 ;
0+
b101 2
b101 6
b1010100000001 .
b1010100000001 5
b1010100000001 >
b111 $
b111 4
b111 =
1!
#1500
0!
#1550
1)
b1 #
b1 <
b10 '
b10 ;
b1101 2
b1101 6
b110100000001 .
b110100000001 5
b110100000001 >
b1000 $
b1000 4
b1000 =
1!
#1600
0!
#1650
10
b1001 1
b1001 7
0)
b0 #
b0 <
b1110 2
b1110 6
b111000001001 .
b111000001001 5
b111000001001 >
b1001 $
b1001 4
b1001 =
1!
#1700
0!
#1750
1%
b11 /
b11 3
b11 8
b0 1
b0 7
00
b1111 2
b1111 6
b111100000011 .
b111100000011 5
b111100000011 >
b1010 $
b1010 4
b1010 =
1!
#1800
0!
#1850
1+
b1 '
b1 ;
b100 #
b100 <
b0 /
b0 3
b0 8
0%
b1100 2
b1100 6
b110000000100 .
b110000000100 5
b110000000100 >
b11 $
b11 4
b11 =
1!
#1900
0!
#1950
b0 #
b0 <
b10 '
b10 ;
0+
b1001 2
b1001 6
b100100000000 .
b100100000000 5
b100100000000 >
b100 $
b100 4
b100 =
1!
#2000
0!
#2050
1)
b10 #
b10 <
b1101 2
b1101 6
b110100000010 .
b110100000010 5
b110100000010 >
b101 $
b101 4
b101 =
1!
#2100
0!
#2150
1+
b0 '
b0 ;
b10001 (
b10001 :
0)
b0 #
b0 <
b1010 2
b1010 6
b1101000010001 .
b1101000010001 5
b1101000010001 >
b110 $
b110 4
b110 =
1!
#2200
0!
#2250
b1 #
b1 <
b0 (
b0 :
b1 '
b1 ;
0+
b101 2
b101 6
b1010100000001 .
b1010100000001 5
b1010100000001 >
b111 $
b111 4
b111 =
1!
#2300
0!
#2350
1)
b1 #
b1 <
b10 '
b10 ;
b1101 2
b1101 6
b110100000001 .
b110100000001 5
b110100000001 >
b1000 $
b1000 4
b1000 =
1!
#2400
0!
#2450
10
b1001 1
b1001 7
0)
b0 #
b0 <
b1110 2
b1110 6
b111000001001 .
b111000001001 5
b111000001001 >
b1001 $
b1001 4
b1001 =
1!
#2500
0!
#2550
1%
b11 /
b11 3
b11 8
b0 1
b0 7
00
b1111 2
b1111 6
b111100000011 .
b111100000011 5
b111100000011 >
b1010 $
b1010 4
b1010 =
1!
#2600
0!
#2650
1+
b1 '
b1 ;
b100 #
b100 <
b0 /
b0 3
b0 8
0%
b1100 2
b1100 6
b110000000100 .
b110000000100 5
b110000000100 >
b11 $
b11 4
b11 =
1!
#2700
0!
#2750
b0 #
b0 <
b10 '
b10 ;
0+
b1001 2
b1001 6
b100100000000 .
b100100000000 5
b100100000000 >
b100 $
b100 4
b100 =
1!
#2800
0!
#2850
1)
b10 #
b10 <
b1101 2
b1101 6
b110100000010 .
b110100000010 5
b110100000010 >
b101 $
b101 4
b101 =
1!
#2900
0!
#2950
1+
b0 '
b0 ;
b10001 (
b10001 :
0)
b0 #
b0 <
b1010 2
b1010 6
b1101000010001 .
b1101000010001 5
b1101000010001 >
b110 $
b110 4
b110 =
1!
#3000
0!
#3050
b1 #
b1 <
b0 (
b0 :
b1 '
b1 ;
0+
b101 2
b101 6
b1010100000001 .
b1010100000001 5
b1010100000001 >
b111 $
b111 4
b111 =
1!
#3100
0!
#3150
1)
b1 #
b1 <
b10 '
b10 ;
b1101 2
b1101 6
b110100000001 .
b110100000001 5
b110100000001 >
b1000 $
b1000 4
b1000 =
1!
#3200
0!
#3250
10
b1001 1
b1001 7
0)
b0 #
b0 <
b1110 2
b1110 6
b111000001001 .
b111000001001 5
b111000001001 >
b1001 $
b1001 4
b1001 =
1!
#3300
0!
#3350
1%
b11 /
b11 3
b11 8
b0 1
b0 7
00
b1111 2
b1111 6
b111100000011 .
b111100000011 5
b111100000011 >
b1010 $
b1010 4
b1010 =
1!
#3400
0!
#3450
1+
b1 '
b1 ;
b100 #
b100 <
b0 /
b0 3
b0 8
0%
b1100 2
b1100 6
b110000000100 .
b110000000100 5
b110000000100 >
b11 $
b11 4
b11 =
1!
#3500
0!
#3550
b0 #
b0 <
b10 '
b10 ;
0+
b1001 2
b1001 6
b100100000000 .
b100100000000 5
b100100000000 >
b100 $
b100 4
b100 =
1!
#3600
0!
#3650
1)
b10 #
b10 <
b1101 2
b1101 6
b110100000010 .
b110100000010 5
b110100000010 >
b101 $
b101 4
b101 =
1!
#3700
0!
#3750
1+
b0 '
b0 ;
b10001 (
b10001 :
0)
b0 #
b0 <
b1010 2
b1010 6
b1101000010001 .
b1101000010001 5
b1101000010001 >
b110 $
b110 4
b110 =
1!
#3800
0!
#3850
b1 #
b1 <
b0 (
b0 :
b1 '
b1 ;
0+
b101 2
b101 6
b1010100000001 .
b1010100000001 5
b1010100000001 >
b111 $
b111 4
b111 =
1!
#3900
0!
#3950
1)
b1 #
b1 <
b10 '
b10 ;
b1101 2
b1101 6
b110100000001 .
b110100000001 5
b110100000001 >
b1000 $
b1000 4
b1000 =
1!
#4000
0!
#4050
10
b1001 1
b1001 7
0)
b0 #
b0 <
b1110 2
b1110 6
b111000001001 .
b111000001001 5
b111000001001 >
b1001 $
b1001 4
b1001 =
1!
#4100
0!
#4150
1%
b11 /
b11 3
b11 8
b0 1
b0 7
00
b1111 2
b1111 6
b111100000011 .
b111100000011 5
b111100000011 >
b1010 $
b1010 4
b1010 =
1!
#4200
0!
#4250
1+
b1 '
b1 ;
b100 #
b100 <
b0 /
b0 3
b0 8
0%
b1100 2
b1100 6
b110000000100 .
b110000000100 5
b110000000100 >
b11 $
b11 4
b11 =
1!
#4300
0!
#4350
b0 #
b0 <
b10 '
b10 ;
0+
b1001 2
b1001 6
b100100000000 .
b100100000000 5
b100100000000 >
b100 $
b100 4
b100 =
1!
#4400
0!
#4450
1)
b10 #
b10 <
b1101 2
b1101 6
b110100000010 .
b110100000010 5
b110100000010 >
b101 $
b101 4
b101 =
1!
#4500
0!
#4550
1+
b0 '
b0 ;
b10001 (
b10001 :
0)
b0 #
b0 <
b1010 2
b1010 6
b1101000010001 .
b1101000010001 5
b1101000010001 >
b110 $
b110 4
b110 =
1!
#4600
0!
#4650
b1 #
b1 <
b0 (
b0 :
b1 '
b1 ;
0+
b101 2
b101 6
b1010100000001 .
b1010100000001 5
b1010100000001 >
b111 $
b111 4
b111 =
1!
#4700
0!
#4750
1)
b1 #
b1 <
b10 '
b10 ;
b1101 2
b1101 6
b110100000001 .
b110100000001 5
b110100000001 >
b1000 $
b1000 4
b1000 =
1!
#4800
0!
#4850
10
b1001 1
b1001 7
0)
b0 #
b0 <
b1110 2
b1110 6
b111000001001 .
b111000001001 5
b111000001001 >
b1001 $
b1001 4
b1001 =
1!
#4900
0!
#4950
1%
b11 /
b11 3
b11 8
b0 1
b0 7
00
b1111 2
b1111 6
b111100000011 .
b111100000011 5
b111100000011 >
b1010 $
b1010 4
b1010 =
1!
#5000
0!
#5050
1+
b1 '
b1 ;
b100 #
b100 <
b0 /
b0 3
b0 8
0%
b1100 2
b1100 6
b110000000100 .
b110000000100 5
b110000000100 >
b11 $
b11 4
b11 =
1!
#5100
0!
#5150
b0 #
b0 <
b10 '
b10 ;
0+
b1001 2
b1001 6
b100100000000 .
b100100000000 5
b100100000000 >
b100 $
b100 4
b100 =
1!
#5200
0!
#5250
1)
b10 #
b10 <
b1101 2
b1101 6
b110100000010 .
b110100000010 5
b110100000010 >
b101 $
b101 4
b101 =
1!
#5300
0!
#5350
1+
b0 '
b0 ;
b10001 (
b10001 :
0)
b0 #
b0 <
b1010 2
b1010 6
b1101000010001 .
b1101000010001 5
b1101000010001 >
b110 $
b110 4
b110 =
1!
#5400
0!
#5450
b1 #
b1 <
b0 (
b0 :
b1 '
b1 ;
0+
b101 2
b101 6
b1010100000001 .
b1010100000001 5
b1010100000001 >
b111 $
b111 4
b111 =
1!
#5500
0!
#5550
1)
b1 #
b1 <
b10 '
b10 ;
b1101 2
b1101 6
b110100000001 .
b110100000001 5
b110100000001 >
b1000 $
b1000 4
b1000 =
1!
#5600
0!
#5650
10
b1001 1
b1001 7
0)
b0 #
b0 <
b1110 2
b1110 6
b111000001001 .
b111000001001 5
b111000001001 >
b1001 $
b1001 4
b1001 =
1!
#5700
0!
#5750
1%
b11 /
b11 3
b11 8
b0 1
b0 7
00
b1111 2
b1111 6
b111100000011 .
b111100000011 5
b111100000011 >
b1010 $
b1010 4
b1010 =
1!
#5800
0!
#5850
1+
b1 '
b1 ;
b100 #
b100 <
b0 /
b0 3
b0 8
0%
b1100 2
b1100 6
b110000000100 .
b110000000100 5
b110000000100 >
b11 $
b11 4
b11 =
1!
#5900
0!
#5950
b0 #
b0 <
b10 '
b10 ;
0+
b1001 2
b1001 6
b100100000000 .
b100100000000 5
b100100000000 >
b100 $
b100 4
b100 =
1!
#6000
0!
#6050
1)
b10 #
b10 <
b1101 2
b1101 6
b110100000010 .
b110100000010 5
b110100000010 >
b101 $
b101 4
b101 =
1!
#6100
0!
#6150
1+
b0 '
b0 ;
b10001 (
b10001 :
0)
b0 #
b0 <
b1010 2
b1010 6
b1101000010001 .
b1101000010001 5
b1101000010001 >
b110 $
b110 4
b110 =
1!
#6200
0!
#6250
b1 #
b1 <
b0 (
b0 :
b1 '
b1 ;
0+
b101 2
b101 6
b1010100000001 .
b1010100000001 5
b1010100000001 >
b111 $
b111 4
b111 =
1!
#6300
0!
#6350
1)
b1 #
b1 <
b10 '
b10 ;
b1101 2
b1101 6
b110100000001 .
b110100000001 5
b110100000001 >
b1000 $
b1000 4
b1000 =
1!
#6400
0!
#6450
10
b1001 1
b1001 7
0)
b0 #
b0 <
b1110 2
b1110 6
b111000001001 .
b111000001001 5
b111000001001 >
b1001 $
b1001 4
b1001 =
1!
#6500
0!
#6550
1%
b11 /
b11 3
b11 8
b0 1
b0 7
00
b1111 2
b1111 6
b111100000011 .
b111100000011 5
b111100000011 >
b1010 $
b1010 4
b1010 =
1!
#6600
0!
#6650
1+
b1 '
b1 ;
b100 #
b100 <
b0 /
b0 3
b0 8
0%
b1100 2
b1100 6
b110000000100 .
b110000000100 5
b110000000100 >
b11 $
b11 4
b11 =
1!
#6700
0!
#6750
b0 #
b0 <
b10 '
b10 ;
0+
b1001 2
b1001 6
b100100000000 .
b100100000000 5
b100100000000 >
b100 $
b100 4
b100 =
1!
#6800
0!
#6850
1)
b10 #
b10 <
b1101 2
b1101 6
b110100000010 .
b110100000010 5
b110100000010 >
b101 $
b101 4
b101 =
1!
#6900
0!
#6950
1+
b0 '
b0 ;
b10001 (
b10001 :
0)
b0 #
b0 <
b1010 2
b1010 6
b1101000010001 .
b1101000010001 5
b1101000010001 >
b110 $
b110 4
b110 =
1!
#7000
0!
#7050
b1 #
b1 <
b0 (
b0 :
b1 '
b1 ;
0+
b101 2
b101 6
b1010100000001 .
b1010100000001 5
b1010100000001 >
b111 $
b111 4
b111 =
1!
#7100
0!
#7150
1)
b1 #
b1 <
b10 '
b10 ;
b1101 2
b1101 6
b110100000001 .
b110100000001 5
b110100000001 >
b1000 $
b1000 4
b1000 =
1!
#7200
0!
#7250
10
b1001 1
b1001 7
0)
b0 #
b0 <
b1110 2
b1110 6
b111000001001 .
b111000001001 5
b111000001001 >
b1001 $
b1001 4
b1001 =
1!
#7300
0!
#7350
1%
b11 /
b11 3
b11 8
b0 1
b0 7
00
b1111 2
b1111 6
b111100000011 .
b111100000011 5
b111100000011 >
b1010 $
b1010 4
b1010 =
1!
#7400
0!
#7450
1+
b1 '
b1 ;
b100 #
b100 <
b0 /
b0 3
b0 8
0%
b1100 2
b1100 6
b110000000100 .
b110000000100 5
b110000000100 >
b11 $
b11 4
b11 =
1!
#7500
0!
#7550
b0 #
b0 <
b10 '
b10 ;
0+
b1001 2
b1001 6
b100100000000 .
b100100000000 5
b100100000000 >
b100 $
b100 4
b100 =
1!
#7600
0!
#7650
1)
b10 #
b10 <
b1101 2
b1101 6
b110100000010 .
b110100000010 5
b110100000010 >
b101 $
b101 4
b101 =
1!
#7700
0!
#7750
1+
b0 '
b0 ;
b10001 (
b10001 :
0)
b0 #
b0 <
b1010 2
b1010 6
b1101000010001 .
b1101000010001 5
b1101000010001 >
b110 $
b110 4
b110 =
1!
#7800
0!
#7850
b1 #
b1 <
b0 (
b0 :
b1 '
b1 ;
0+
b101 2
b101 6
b1010100000001 .
b1010100000001 5
b1010100000001 >
b111 $
b111 4
b111 =
1!
#7900
0!
#7950
1)
b1 #
b1 <
b10 '
b10 ;
b1101 2
b1101 6
b110100000001 .
b110100000001 5
b110100000001 >
b1000 $
b1000 4
b1000 =
1!
#8000
0!
#8050
10
b1001 1
b1001 7
0)
b0 #
b0 <
b1110 2
b1110 6
b111000001001 .
b111000001001 5
b111000001001 >
b1001 $
b1001 4
b1001 =
1!
#8100
0!
#8150
1%
b11 /
b11 3
b11 8
b0 1
b0 7
00
b1111 2
b1111 6
b111100000011 .
b111100000011 5
b111100000011 >
b1010 $
b1010 4
b1010 =
1!
#8200
0!
#8250
1+
b1 '
b1 ;
b100 #
b100 <
b0 /
b0 3
b0 8
0%
b1100 2
b1100 6
b110000000100 .
b110000000100 5
b110000000100 >
b11 $
b11 4
b11 =
1!
#8300
0!
#8350
b0 #
b0 <
b10 '
b10 ;
0+
b1001 2
b1001 6
b100100000000 .
b100100000000 5
b100100000000 >
b100 $
b100 4
b100 =
1!
#8400
0!
#8450
1)
b10 #
b10 <
b1101 2
b1101 6
b110100000010 .
b110100000010 5
b110100000010 >
b101 $
b101 4
b101 =
1!
#8500
0!
#8550
1+
b0 '
b0 ;
b10001 (
b10001 :
0)
b0 #
b0 <
b1010 2
b1010 6
b1101000010001 .
b1101000010001 5
b1101000010001 >
b110 $
b110 4
b110 =
1!
#8600
0!
#8650
b1 #
b1 <
b0 (
b0 :
b1 '
b1 ;
0+
b101 2
b101 6
b1010100000001 .
b1010100000001 5
b1010100000001 >
b111 $
b111 4
b111 =
1!
#8700
0!
#8750
1)
b1 #
b1 <
b10 '
b10 ;
b1101 2
b1101 6
b110100000001 .
b110100000001 5
b110100000001 >
b1000 $
b1000 4
b1000 =
1!
#8800
0!
#8850
10
b1001 1
b1001 7
0)
b0 #
b0 <
b1110 2
b1110 6
b111000001001 .
b111000001001 5
b111000001001 >
b1001 $
b1001 4
b1001 =
1!
#8900
0!
#8950
1%
b11 /
b11 3
b11 8
b0 1
b0 7
00
b1111 2
b1111 6
b111100000011 .
b111100000011 5
b111100000011 >
b1010 $
b1010 4
b1010 =
1!
#9000
0!
#9050
1+
b1 '
b1 ;
b100 #
b100 <
b0 /
b0 3
b0 8
0%
b1100 2
b1100 6
b110000000100 .
b110000000100 5
b110000000100 >
b11 $
b11 4
b11 =
1!
#9100
0!
#9150
b0 #
b0 <
b10 '
b10 ;
0+
b1001 2
b1001 6
b100100000000 .
b100100000000 5
b100100000000 >
b100 $
b100 4
b100 =
1!
#9200
0!
#9250
1)
b10 #
b10 <
b1101 2
b1101 6
b110100000010 .
b110100000010 5
b110100000010 >
b101 $
b101 4
b101 =
1!
#9300
0!
